stactools/sentinel3/__init__.py
stactools/sentinel3/commands.py
stactools/sentinel3/constants.py
stactools/sentinel3/file_extension_updated.py
stactools/sentinel3/metadata_links.py
stactools/sentinel3/product_metadata.py
stactools/sentinel3/properties.py
stactools/sentinel3/stac.py
stactools/sentinel3/xml.py
stactools_sentinel3-0.4.0.dist-info/LICENSE
stactools_sentinel3-0.4.0.dist-info/METADATA
stactools_sentinel3-0.4.0.dist-info/WHEEL
stactools_sentinel3-0.4.0.dist-info/top_level.txt
stactools_sentinel3-0.4.0.dist-info/RECORD
