Metadata-Version: 2.1
Name: stactools-sentinel3
Version: 0.4.0
Summary: Stactools package for Sentinel-3 OLCI (level 1 EFR, ERR and level 2 LFR, LRR, WFR), SLSTR (level 1 RBT and level 2 FRP, LST, WST), SRAL (level 2 LAN, WAT), and SYNERGY (level 2 AOD, SYN, V10, VG1, VGP) scenes.
Home-page: https://github.com/chorng/sentinel3
Author: Chung-Xiang Hong & William Ray
Author-email: chung.horng@sinergise.com, william.ray@sinergise.com
Project-URL: Issues, https://github.com/chorng/sentinel3/issues
Keywords: stactools,pystac,catalog,STAC,sentinel,OLCI,EFR,ERR,LFR,LRR,WFR,SLSTR,RBT,FRP,LWT,WST,SRAL,LAN,WAT,SYNERGY,AOD,SYN,V10,VG1,VGP
Classifier: Development Status :: 4 - Beta
Classifier: License :: OSI Approved :: Apache Software License
Classifier: Programming Language :: Python :: 3.8
Classifier: Programming Language :: Python :: 3.9
Classifier: Programming Language :: Python :: 3.10
Classifier: Programming Language :: Python :: 3.11
License-File: LICENSE
Requires-Dist: stactools (>=0.4)
Requires-Dist: netCDF4 (>=1.6.3)
